aeosa.pth
aeosa/osax.py
aeosa/mactypes.py
aeosa/aem/ae.cpython-313-darwin.so
aeosa/aem/aemsend.py
aeosa/aem/findapp.py
aeosa/aem/aemconnect.py
aeosa/aem/typewrappers.py
aeosa/aem/__init__.py
aeosa/aem/kae.py
aeosa/aem/aemreference.py
aeosa/aem/aemcodecs.py
aeosa/aem/mactypes.py
aeosa/appscript/keywordwrapper.py
aeosa/appscript/__init__.py
aeosa/appscript/referencerenderer.py
aeosa/appscript/aeteparser.py
aeosa/appscript/reservedkeywords.py
aeosa/appscript/reference.py
aeosa/appscript/sdefparser.py
aeosa/appscript/defaultterminology.py
aeosa/appscript/terminology.py
aeosa/appscript/genericreference.py
appscript-1.3.0.dist-info/RECORD
appscript-1.3.0.dist-info/WHEEL
appscript-1.3.0.dist-info/top_level.txt
appscript-1.3.0.dist-info/METADATA
