Metadata-Version: 2.1
Name: appscript
Version: 1.3.0
Summary: Control AppleScriptable applications from Python.
Home-page: http://appscript.sourceforge.net
License: Public Domain
Platform: Mac OS X
Classifier: License :: Public Domain
Classifier: Development Status :: 5 - Production/Stable
Classifier: Operating System :: MacOS :: MacOS X
Classifier: Programming Language :: Python :: 3
